aligem/__init__.py
aligem/command_line.py
aligem/config.py
aligem/jobs.py
aligem/sandbox_token.py
aligem/test_config.py
aligem/test_jobs.py
aligem/token.py
aligem-1.1.0.dist-info/DESCRIPTION.rst
aligem-1.1.0.dist-info/METADATA
aligem-1.1.0.dist-info/RECORD
aligem-1.1.0.dist-info/WHEEL
aligem-1.1.0.dist-info/entry_points.txt
aligem-1.1.0.dist-info/metadata.json
aligem-1.1.0.dist-info/top_level.txt
