Metadata-Version: 2.0
Name: aligem
Version: 1.1.0
Summary: ALICE Grid Enviroment Manager
Home-page: http://github.com/vpacik/aligem
Author: Vojtech Pacik
Author-email: vojtech.pacik@cern.ch
License: GPL-3.0
Keywords: aligem ALICE CERN high energy physics
Platform: UNKNOWN
Classifier: Development Status :: 5 - Production/Stable
Classifier: License :: OSI Approved :: GNU General Public License v3 (GPLv3)
Classifier: Programming Language :: Python :: 2.7
Classifier: Intended Audience :: Science/Research
Classifier: Topic :: Scientific/Engineering :: Physics
Classifier: Natural Language :: English
